neural_anthropometer/__init__.py
neural_anthropometer/annotate/__init__.py
neural_anthropometer/annotate/annotate_with_Sharmeam_and_Calvis.py
neural_anthropometer/dataset/NeuralAnthropometerDataset.py
neural_anthropometer/dataset/__init__.py
neural_anthropometer/display/__init__.py
neural_anthropometer/display/display_image_grid.py
neural_anthropometer/display/display_subject_sharmean_and_calvis_with_vedo_and_trimesh.py
neural_anthropometer/neural_anthropometer/NeuralAnthropometer.py
neural_anthropometer/neural_anthropometer/__init__.py
neural_anthropometer/sharmeam/__init__.py
neural_anthropometer/sharmeam/sharmeam.py
neural_anthropometer/smpl/__init__.py
neural_anthropometer/smpl/smpl.py
neural_anthropometer/transform/NeuralAnthropometerTransform.py
neural_anthropometer/transform/__init__.py
neural_anthropometer/utils/__init__.py
neural_anthropometer/utils/utils.py
neural_anthropometer-0.0.3.dist-info/LICENSE.md
neural_anthropometer-0.0.3.dist-info/METADATA
neural_anthropometer-0.0.3.dist-info/WHEEL
neural_anthropometer-0.0.3.dist-info/top_level.txt
neural_anthropometer-0.0.3.dist-info/RECORD
