Metadata-Version: 2.1
Name: neural-anthropometer
Version: 0.0.3
Summary: A Neural Anthropometer Learning from Body Dimensions Computed on Human 3D Meshes
Home-page: https://github.com/neoglez/neural-antropometer
Author: ['Yansel González Tejeda', 'Helmut A. Mayer']
Author-email: neoglez@gmail.com
Classifier: Programming Language :: Python :: 2
Classifier: Programming Language :: Python :: 3
Classifier: License :: OSI Approved :: MIT License
Classifier: Operating System :: OS Independent
License-File: LICENSE.md
Requires-Dist: numpy
Requires-Dist: opencv-python
